{
    "code": null,
    "data": {
        "today": [{
                  "t": "2018-08-08 13:20",
                  "v": "2796.6528069607334"
                  },
                  {
                  "t": "2018-08-08 13:21",
                  "v": "3285.682935438669"
                  },
                  {
                  "t": "2018-08-08 13:22",
                  "v": "3550.991458807288"
                  },
                  {
                  "t": "2018-08-08 13:23",
                  "v": "3769.4790341794396"
                  },
                  {
                  "t": "2018-08-08 13:24",
                  "v": "1319.3829947231975"
                  },
                  {
                  "t": "2018-08-08 13:25",
                  "v": "2186.4987464085375"
                  },
                  {
                  "t": "2018-08-08 13:26",
                  "v": "4072.349683395638"
                  },
                  {
                  "t": "2018-08-08 13:27",
                  "v": "3894.5168761614186"
                  },
                  {
                  "t": "2018-08-08 13:28",
                  "v": "4016.717526634793"
                  },
                  {
                  "t": "2018-08-08 13:29",
                  "v": "1814.1937380485042"
                  },
                  {
                  "t": "2018-08-08 13:30",
                  "v": "1941.8924721729445"
                  },
                  {
                  "t": "2018-08-08 13:31",
                  "v": "2946.887500773971"
                  },
                  {
                  "t": "2018-08-08 13:32",
                  "v": "2223.137262657748"
                  },
                  {
                  "t": "2018-08-08 13:33",
                  "v": "2661.9406027118475"
                  },
                  {
                  "t": "2018-08-08 13:34",
                  "v": "2873.7197104740962"
                  },
                  {
                  "t": "2018-08-08 13:35",
                  "v": "1111.469621274312"
                  },
                  {
                  "t": "2018-08-08 13:36",
                  "v": "2946.574277831888"
                  },
                  {
                  "t": "2018-08-08 13:37",
                  "v": "3744.8446584049693"
                  },
                  {
                  "t": "2018-08-08 13:38",
                  "v": "1938.001990805584"
                  },
                  {
                  "t": "2018-08-08 13:39",
                  "v": "1927.112215688953"
                  },
                  {
                  "t": "2018-08-08 13:40",
                  "v": "2627.721307296225"
                  },
                  {
                  "t": "2018-08-08 13:41",
                  "v": "4070.5843138753507"
                  },
                  {
                  "t": "2018-08-08 13:42",
                  "v": "3263.8170249156256"
                  },
                  {
                  "t": "2018-08-08 13:43",
                  "v": "3460.086705491238"
                  },
                  {
                  "t": "2018-08-08 13:44",
                  "v": "2143.0689241252585"
                  },
                  {
                  "t": "2018-08-08 13:45",
                  "v": "3122.2815673673667"
                  },
                  {
                  "t": "2018-08-08 13:46",
                  "v": "1679.4444543790567"
                  },
                  {
                  "t": "2018-08-08 13:47",
                  "v": "2773.9448366875295"
                  },
                  {
                  "t": "2018-08-08 13:48",
                  "v": "2714.0401231621645"
                  },
                  {
                  "t": "2018-08-08 13:49",
                  "v": "3274.589744347761"
                  },
                  {
                  "t": "2018-08-08 13:50",
                  "v": "2737.060251630307"
                  },
                  {
                  "t": "2018-08-08 13:51",
                  "v": "3710.2245503585777"
                  },
                  {
                  "t": "2018-08-08 13:52",
                  "v": "3084.3538776680407"
                  },
                  {
                  "t": "2018-08-08 13:53",
                  "v": "2938.8535935582295"
                  },
                  {
                  "t": "2018-08-08 13:54",
                  "v": "2770.2683109795544"
                  },
                  {
                  "t": "2018-08-08 13:55",
                  "v": "2004.7280291025793"
                  },
                  {
                  "t": "2018-08-08 13:56",
                  "v": "2400.361479852174"
                  },
                  {
                  "t": "2018-08-08 13:57",
                  "v": "4968.863782678138"
                  },
                  {
                  "t": "2018-08-08 13:58",
                  "v": "3632.905957429242"
                  },
                  {
                  "t": "2018-08-08 13:59",
                  "v": "2512.8080381121254"
                  },
                  {
                  "t": "2018-08-08 14:00",
                  "v": "3621.941106089156"
                  },
                  {
                  "t": "2018-08-08 14:01",
                  "v": "2549.236155126301"
                  },
                  {
                  "t": "2018-08-08 14:02",
                  "v": "3267.561732785257"
                  },
                  {
                  "t": "2018-08-08 14:03",
                  "v": "3317.1007806809857"
                  },
                  {
                  "t": "2018-08-08 14:04",
                  "v": "4713.124738602528"
                  },
                  {
                  "t": "2018-08-08 14:05",
                  "v": "3370.696429702384"
                  },
                  {
                  "t": "2018-08-08 14:06",
                  "v": "2252.242522156099"
                  },
                  {
                  "t": "2018-08-08 14:07",
                  "v": "2991.142303294342"
                  },
                  {
                  "t": "2018-08-08 14:08",
                  "v": "2836.5759394934707"
                  },
                  {
                  "t": "2018-08-08 14:09",
                  "v": "2355.428077505133"
                  },
                  {
                  "t": "2018-08-08 14:10",
                  "v": "3473.6276203751036"
                  },
                  {
                  "t": "2018-08-08 14:11",
                  "v": "1792.3066030431803"
                  },
                  {
                  "t": "2018-08-08 14:12",
                  "v": "2167.7292294607355"
                  },
                  {
                  "t": "2018-08-08 14:13",
                  "v": "3635.959695113916"
                  },
                  {
                  "t": "2018-08-08 14:14",
                  "v": "3075.347047308208"
                  },
                  {
                  "t": "2018-08-08 14:15",
                  "v": "2698.6579323375754"
                  },
                  {
                  "t": "2018-08-08 14:16",
                  "v": "2509.6561661363503"
                  },
                  {
                  "t": "2018-08-08 14:17",
                  "v": "2431.5027675503575"
                  },
                  {
                  "t": "2018-08-08 14:18",
                  "v": "2329.7218903962707"
                  },
                  {
                  "t": "2018-08-08 14:19",
                  "v": "4075.064172723143"
                  },
                  {
                  "t": "2018-08-08 14:20",
                  "v": "2837.518079929345"
                  },
                  {
                  "t": "2018-08-08 14:21",
                  "v": "5001.868743624986"
                  },
                  {
                  "t": "2018-08-08 14:22",
                  "v": "2581.4040951531297"
                  },
                  {
                  "t": "2018-08-08 14:23",
                  "v": "2706.283005129798"
                  },
                  {
                  "t": "2018-08-08 14:24",
                  "v": "1427.5699160357049"
                  },
                  {
                  "t": "2018-08-08 14:25",
                  "v": "3732.3278246486816"
                  },
                  {
                  "t": "2018-08-08 14:26",
                  "v": "3911.3532137475163"
                  },
                  {
                  "t": "2018-08-08 14:27",
                  "v": "2030.0003447336235"
                  },
                  {
                  "t": "2018-08-08 14:28",
                  "v": "2718.219133013831"
                  },
                  {
                  "t": "2018-08-08 14:29",
                  "v": "2656.3056706982525"
                  },
                  {
                  "t": "2018-08-08 14:30",
                  "v": "2669.5873312243248"
                  },
                  {
                  "t": "2018-08-08 14:31",
                  "v": "2283.7170730697794"
                  },
                  {
                  "t": "2018-08-08 14:32",
                  "v": "2801.5784756305543"
                  },
                  {
                  "t": "2018-08-08 14:33",
                  "v": "2655.8963599406193"
                  },
                  {
                  "t": "2018-08-08 14:34",
                  "v": "2525.146193583426"
                  },
                  {
                  "t": "2018-08-08 14:35",
                  "v": "2597.9394433940975"
                  },
                  {
                  "t": "2018-08-08 14:36",
                  "v": "3443.948422197559"
                  },
                  {
                  "t": "2018-08-08 14:37",
                  "v": "3833.705639627711"
                  },
                  {
                  "t": "2018-08-08 14:38",
                  "v": "2681.703578457586"
                  },
                  {
                  "t": "2018-08-08 14:39",
                  "v": "3234.1485008104783"
                  },
                  {
                  "t": "2018-08-08 14:40",
                  "v": "2533.6689287659847"
                  },
                  {
                  "t": "2018-08-08 14:41",
                  "v": "3922.7681636011566"
                  },
                  {
                  "t": "2018-08-08 14:42",
                  "v": "1907.2665749798107"
                  },
                  {
                  "t": "2018-08-08 14:43",
                  "v": "2288.993531267349"
                  },
                  {
                  "t": "2018-08-08 14:44",
                  "v": "3354.7759351229383"
                  },
                  {
                  "t": "2018-08-08 14:45",
                  "v": "4137.505804652058"
                  },
                  {
                  "t": "2018-08-08 14:46",
                  "v": "3026.3993947269573"
                  },
                  {
                  "t": "2018-08-08 14:47",
                  "v": "2822.873565677917"
                  },
                  {
                  "t": "2018-08-08 14:48",
                  "v": "4084.901472646693"
                  },
                  {
                  "t": "2018-08-08 14:49",
                  "v": "2989.162769312591"
                  },
                  {
                  "t": "2018-08-08 14:50",
                  "v": "4023.409022702075"
                  },
                  {
                  "t": "2018-08-08 14:51",
                  "v": "2501.6184137282016"
                  },
                  {
                  "t": "2018-08-08 14:52",
                  "v": "3915.8542918275552"
                  },
                  {
                  "t": "2018-08-08 14:53",
                  "v": "2089.1562377895452"
                  },
                  {
                  "t": "2018-08-08 14:54",
                  "v": "2404.930084373156"
                  },
                  {
                  "t": "2018-08-08 14:55",
                  "v": "3835.542242610406"
                  },
                  {
                  "t": "2018-08-08 14:56",
                  "v": "2195.3187989793005"
                  },
                  {
                  "t": "2018-08-08 14:57",
                  "v": "2963.779374203624"
                  },
                  {
                  "t": "2018-08-08 14:58",
                  "v": "3470.347221207384"
                  },
                  {
                  "t": "2018-08-08 14:59",
                  "v": "1352.3615208993224"
                  },
                  {
                  "t": "2018-08-08 15:00",
                  "v": "4488.109488169056"
                  },
                  {
                  "t": "2018-08-08 15:01",
                  "v": "2403.6940440366343"
                  },
                  {
                  "t": "2018-08-08 15:02",
                  "v": "3638.491166076261"
                  },
                  {
                  "t": "2018-08-08 15:03",
                  "v": "4254.12269316203"
                  },
                  {
                  "t": "2018-08-08 15:04",
                  "v": "2955.418568483564"
                  },
                  {
                  "t": "2018-08-08 15:05",
                  "v": "2871.651849737985"
                  },
                  {
                  "t": "2018-08-08 15:06",
                  "v": "3979.047146246824"
                  },
                  {
                  "t": "2018-08-08 15:07",
                  "v": "2331.574988777382"
                  },
                  {
                  "t": "2018-08-08 15:08",
                  "v": "3450.494330287585"
                  },
                  {
                  "t": "2018-08-08 15:09",
                  "v": "3491.879301474192"
                  },
                  {
                  "t": "2018-08-08 15:10",
                  "v": "2597.1125205900616"
                  },
                  {
                  "t": "2018-08-08 15:11",
                  "v": "3409.4281270313672"
                  },
                  {
                  "t": "2018-08-08 15:12",
                  "v": "3729.187727074941"
                  },
                  {
                  "t": "2018-08-08 15:13",
                  "v": "3144.5661810076253"
                  },
                  {
                  "t": "2018-08-08 15:14",
                  "v": "3392.677511260924"
                  },
                  {
                  "t": "2018-08-08 15:15",
                  "v": "3595.930389020081"
                  },
                  {
                  "t": "2018-08-08 15:16",
                  "v": "4173.804403643576"
                  },
                  {
                  "t": "2018-08-08 15:17",
                  "v": "3688.893697999173"
                  },
                  {
                  "t": "2018-08-08 15:18",
                  "v": "2230.1149054137018"
                  },
                  {
                  "t": "2018-08-08 15:19",
                  "v": "2110.2060808189026"
                  },
                  {
                  "t": "2018-08-08 15:20",
                  "v": "4724.402792455141"
                  },
                  {
                  "t": "2018-08-08 15:21",
                  "v": "6603.945257576068"
                  },
                  {
                  "t": "2018-08-08 15:22",
                  "v": "6668.930046025575"
                  },
                  {
                  "t": "2018-08-08 15:23",
                  "v": "6158.835972939188"
                  },
                  {
                  "t": "2018-08-08 15:24",
                  "v": "1846.0563754652112"
                  },
                  {
                  "t": "2018-08-08 15:25",
                  "v": "3709.602222309645"
                  },
                  {
                  "t": "2018-08-08 15:26",
                  "v": "3698.1289481593167"
                  },
                  {
                  "t": "2018-08-08 15:27",
                  "v": "1248.790359882315"
                  },
                  {
                  "t": "2018-08-08 15:28",
                  "v": "2640.2754130434923"
                  },
                  {
                  "t": "2018-08-08 15:29",
                  "v": "2074.8669114807444"
                  },
                  {
                  "t": "2018-08-08 15:30",
                  "v": "4107.373130796124"
                  },
                  {
                  "t": "2018-08-08 15:31",
                  "v": "2869.135915929271"
                  },
                  {
                  "t": "2018-08-08 15:32",
                  "v": "2149.4290999921304"
                  },
                  {
                  "t": "2018-08-08 15:33",
                  "v": "3830.3764339282"
                  },
                  {
                  "t": "2018-08-08 15:34",
                  "v": "3106.6768197813435"
                  },
                  {
                  "t": "2018-08-08 15:35",
                  "v": "4883.315151551313"
                  }
                  ],
        "yestoday": [{
                     "t": "2018-08-07 19:21",
                     "v": "2674.4146610834687"
                     },
                     {
                     "t": "2018-08-07 19:22",
                     "v": "2930.4285680794164"
                     },
                     {
                     "t": "2018-08-07 19:23",
                     "v": "3147.6868442529694"
                     },
                     {
                     "t": "2018-08-07 19:24",
                     "v": "988.4599398696328"
                     },
                     {
                     "t": "2018-08-07 19:25",
                     "v": "4940.101212901567"
                     },
                     {
                     "t": "2018-08-07 19:26",
                     "v": "3286.742364997574"
                     },
                     {
                     "t": "2018-08-07 19:27",
                     "v": "3759.8177491361344"
                     },
                     {
                     "t": "2018-08-07 19:28",
                     "v": "3564.8649181731016"
                     },
                     {
                     "t": "2018-08-07 19:29",
                     "v": "2500.2999687481124"
                     },
                     {
                     "t": "2018-08-07 19:30",
                     "v": "2625.2021944050944"
                     },
                     {
                     "t": "2018-08-07 19:31",
                     "v": "2379.3586966007833"
                     },
                     {
                     "t": "2018-08-07 19:32",
                     "v": "1474.179800003597"
                     },
                     {
                     "t": "2018-08-07 19:33",
                     "v": "4055.6851242479397"
                     },
                     {
                     "t": "2018-08-07 19:34",
                     "v": "3492.8941840733823"
                     },
                     {
                     "t": "2018-08-07 19:35",
                     "v": "2774.198795671326"
                     },
                     {
                     "t": "2018-08-07 19:36",
                     "v": "2360.0991393929226"
                     },
                     {
                     "t": "2018-08-07 19:37",
                     "v": "3015.15562777995"
                     },
                     {
                     "t": "2018-08-07 19:38",
                     "v": "3081.416751321405"
                     },
                     {
                     "t": "2018-08-07 19:39",
                     "v": "4322.603732746284"
                     },
                     {
                     "t": "2018-08-07 19:40",
                     "v": "3272.158014692201"
                     },
                     {
                     "t": "2018-08-07 19:41",
                     "v": "2459.7456214440826"
                     },
                     {
                     "t": "2018-08-07 19:42",
                     "v": "3332.051180804741"
                     },
                     {
                     "t": "2018-08-07 19:43",
                     "v": "1239.7780497599497"
                     },
                     {
                     "t": "2018-08-07 19:44",
                     "v": "2586.5939462797382"
                     },
                     {
                     "t": "2018-08-07 19:45",
                     "v": "2320.2351447640126"
                     },
                     {
                     "t": "2018-08-07 19:46",
                     "v": "2279.7328760663904"
                     },
                     {
                     "t": "2018-08-07 19:47",
                     "v": "3125.812031764568"
                     },
                     {
                     "t": "2018-08-07 19:48",
                     "v": "2948.5927953281916"
                     },
                     {
                     "t": "2018-08-07 19:49",
                     "v": "1923.0825246305512"
                     },
                     {
                     "t": "2018-08-07 19:50",
                     "v": "4976.6290477737175"
                     },
                     {
                     "t": "2018-08-07 19:51",
                     "v": "3970.6238338022363"
                     },
                     {
                     "t": "2018-08-07 19:52",
                     "v": "4101.934163006513"
                     },
                     {
                     "t": "2018-08-07 19:53",
                     "v": "2088.997117373727"
                     },
                     {
                     "t": "2018-08-07 19:54",
                     "v": "1940.4366116318072"
                     },
                     {
                     "t": "2018-08-07 19:55",
                     "v": "3159.023316003083"
                     },
                     {
                     "t": "2018-08-07 19:56",
                     "v": "2986.532303287206"
                     },
                     {
                     "t": "2018-08-07 19:57",
                     "v": "2199.9485524638017"
                     },
                     {
                     "t": "2018-08-07 19:58",
                     "v": "1085.7433577792915"
                     },
                     {
                     "t": "2018-08-07 19:59",
                     "v": "3167.226237826461"
                     },
                     {
                     "t": "2018-08-07 20:00",
                     "v": "4440.386489084905"
                     },
                     {
                     "t": "2018-08-07 20:01",
                     "v": "2687.451447294498"
                     },
                     {
                     "t": "2018-08-07 20:02",
                     "v": "3901.0853549064177"
                     },
                     {
                     "t": "2018-08-07 20:03",
                     "v": "2049.0220799699423"
                     },
                     {
                     "t": "2018-08-07 20:04",
                     "v": "2788.5945831780664"
                     },
                     {
                     "t": "2018-08-07 20:05",
                     "v": "1973.6618813386783"
                     },
                     {
                     "t": "2018-08-07 20:06",
                     "v": "2184.3873120315834"
                     },
                     {
                     "t": "2018-08-07 20:07",
                     "v": "3385.735086271661"
                     },
                     {
                     "t": "2018-08-07 20:08",
                     "v": "2435.1862052681267"
                     },
                     {
                     "t": "2018-08-07 20:09",
                     "v": "2433.8636650361536"
                     },
                     {
                     "t": "2018-08-07 20:10",
                     "v": "3037.456429690786"
                     },
                     {
                     "t": "2018-08-07 20:11",
                     "v": "3686.507071951859"
                     },
                     {
                     "t": "2018-08-07 20:12",
                     "v": "2764.1180553608783"
                     },
                     {
                     "t": "2018-08-07 20:13",
                     "v": "3180.4024704841067"
                     }
                     ]
    },
    "requestId": "0fbc799a-d37c-40d9-98b6-561c9e95a9e7@_@",
    "message": null
}
